datapurify/__init__.py
datapurify/base.py
datapurify/purifier/purifier.py
datapurify/spider/common_spider.py
datapurify/spider/spider.py
datapurify-0.1.1.dist-info/METADATA
datapurify-0.1.1.dist-info/WHEEL
datapurify-0.1.1.dist-info/RECORD
